{"cameraMode":{"drawMode":0,"name":"Shaded","section":"Shading Mode"},"sceneLighting":true,"audioPlay":false,"sceneViewState":{"m_AlwaysRefresh":false,"showFog":true,"showSkybox":true,"showFlares":true,"showImageEffects":true,"showParticleSystems":true,"showVisualEffectGraphs":true,"m_FxEnabled":true},"in2DMode":false,"pivot":{"x":11.329736709594727,"y":3.0908234119415285,"z":2.3694231510162355},"rotation":{"x":-0.1992635428905487,"y":0.5076454281806946,"z":-0.12197726964950562,"w":-0.8292988538742065},"size":0.8660253882408142,"orthographic":false}